cosmoshub/__init__.py
cosmoshub/__main__.py
cosmoshub/client.py
cosmoshub/endpoints.py
cosmoshub/models.py
cosmoshub/releases.py
delos_cosmoshub-0.1.1.dist-info/LICENSE
delos_cosmoshub-0.1.1.dist-info/METADATA
delos_cosmoshub-0.1.1.dist-info/WHEEL
delos_cosmoshub-0.1.1.dist-info/RECORD
