Metadata-Version: 2.1
Name: delos-cosmoshub
Version: 0.1.1
Summary: CosmosHub client.
Keywords: AI,LLM,generative
Author: Maria
Author-email: mariaibanez@delosintelligence.fr
Requires-Python: >=3.11,<4.0
Classifier: Programming Language :: Python :: 3
Classifier: Programming Language :: Python :: 3.11
Classifier: Programming Language :: Python :: 3.12
Classifier: Programming Language :: Python :: 3.13
Requires-Dist: fastapi (>=0.115.5,<0.116.0)
Requires-Dist: requests (>=2.32.3,<3.0.0)
